pyruciw-0.4.0.dist-info/METADATA
pyruciw-0.4.0.dist-info/WHEEL
pyruciw-0.4.0.dist-info/license_files/LICENSE.txt
pyruciw/__init__.py
pyruciw/pyruciw.cpython-312-x86_64-linux-gnu.so
pyruciw-0.4.0.dist-info/RECORD
